MANIFEST.in
Pipfile
README.md
setup.py
scripts/swappy-check
swappy/__init__.py
swappy/swappy.py
swappy.egg-info/PKG-INFO
swappy.egg-info/SOURCES.txt
swappy.egg-info/dependency_links.txt
swappy.egg-info/requires.txt
swappy.egg-info/top_level.txt