Metadata-Version: 2.1
Name: swappy
Version: 1.2.0
Summary: Fast check swap and interact
Home-page: https://github.com/mickbad/swappy
Author: MickBad
Author-email: prog@mickbad.com
License: MIT
Keywords: linux tools fasting swap
Platform: UNKNOWN
Classifier: Programming Language :: Python
Classifier: Development Status :: 4 - Beta
Classifier: License :: OSI Approved :: MIT License
Classifier: Natural Language :: French
Classifier: Environment :: Console
Classifier: Operating System :: POSIX :: Linux
Classifier: Programming Language :: Python :: 3.5
Classifier: Programming Language :: Python :: 3.6
Classifier: Topic :: Software Development :: Libraries
Classifier: Topic :: Utilities
Classifier: Topic :: System
Classifier: Topic :: System :: Monitoring
Classifier: Topic :: System :: Systems Administration
